readgen/__init__.py
readgen/cli.py
readgen/config.py
readgen/generator.py
readgen/utils/__init__.py
readgen/utils/paths.py
tbi_readgen-0.0.21.dist-info/LICENSE
tbi_readgen-0.0.21.dist-info/METADATA
tbi_readgen-0.0.21.dist-info/WHEEL
tbi_readgen-0.0.21.dist-info/entry_points.txt
tbi_readgen-0.0.21.dist-info/top_level.txt
tbi_readgen-0.0.21.dist-info/RECORD
