Metadata-Version: 2.1
Name: tbi-readgen
Version: 0.0.21
Summary: A simple yet powerful Python project README.md generator.
Author-email: Albert Liu <dreamerhyde@gmail.com>
License: MIT
Project-URL: Homepage, https://github.com/TaiwanBigdata/readgen
Project-URL: Repository, https://github.com/TaiwanBigdata/readgen.git
Keywords: readme,generator,markdown,cli
Classifier: Development Status :: 4 - Beta
Classifier: Environment :: Console
Classifier: Intended Audience :: Developers
Classifier: License :: OSI Approved :: MIT License
Classifier: Operating System :: OS Independent
Classifier: Programming Language :: Python :: 3
Classifier: Programming Language :: Python :: 3.8
Classifier: Programming Language :: Python :: 3.9
Classifier: Programming Language :: Python :: 3.10
Classifier: Programming Language :: Python :: 3.11
Classifier: Programming Language :: Python :: 3.12
Classifier: Topic :: Utilities
Requires-Python: >=3.8
License-File: LICENSE
Requires-Dist: tomli>=2.0.0
Requires-Dist: pydantic>=2.0.0
